LICENSE
MANIFEST.in
README.md
USAGE.md
setup.py
tests/__init__.py
tests/__main__.py
timedcapture/__init__.c
timedcapture/__init__.pyx
timedcapture/capture.c
timedcapture/capture.h
timedcapture/capture.pxd
timedcapture.egg-info/PKG-INFO
timedcapture.egg-info/SOURCES.txt
timedcapture.egg-info/dependency_links.txt
timedcapture.egg-info/not-zip-safe
timedcapture.egg-info/requires.txt
timedcapture.egg-info/top_level.txt