Metadata-Version: 2.1
Name: timedcapture
Version: 0.3.2
Summary: a cython-based module to achieve on-time capture through V4L2.
Home-page: https://github.com/gwappa/python-timedcapture
Author: Keisuke Sehara
Author-email: keisuke.sehara@gmail.com
License: MIT
Platform: UNKNOWN
Classifier: Development Status :: 3 - Alpha
Classifier: License :: OSI Approved :: MIT License
Classifier: Programming Language :: Python :: 3
Classifier: Intended Audience :: Science/Research
Classifier: Operating System :: POSIX :: Linux
Classifier: Programming Language :: Cython
Classifier: Topic :: Multimedia :: Video :: Capture
Requires-Python: >=3.6
